{
	"title": "10. 登竜門 (最難関・覚醒)",
	"length": 3450.0,
	"target_time": 120.0,
	"obstacles": [
		{"type": "rapids", "lane": 0, "dist": 40.0},
		{"type": "monkey", "lane": 1, "dist": 65.0},
		{"type": "salmon", "lane": -1, "dist": 90.0},
		{"type": "hook", "lane": 0, "dist": 115.0},
		{"type": "ufo", "lane": 1, "dist": 140.0},
		{"type": "rock", "lane": -1, "dist": 165.0},
		{"type": "rock", "lane": 1, "dist": 165.0},
		{"type": "monkey", "lane": -1, "dist": 195.0},
		{"type": "salmon", "lane": 0, "dist": 220.0},
		{"type": "hook", "lane": 1, "dist": 245.0},
		{"type": "ufo", "lane": -1, "dist": 270.0},
		{"type": "rock", "lane": 0, "dist": 295.0},
		{"type": "rapids", "lane": 1, "dist": 320.0},
		{"type": "rock", "lane": 0, "dist": 350.0},
		{"type": "breakable", "lane": -1, "dist": 375.0},
		{"type": "rock", "lane": 1, "dist": 400.0},
		{"type": "breakable", "lane": 0, "dist": 425.0},
		{"type": "salmon", "lane": -1, "dist": 450.0},
		{"type": "monkey", "lane": 1, "dist": 450.0},
		{"type": "rock", "lane": 0, "dist": 490.0},
		{"type": "rock", "lane": -1, "dist": 520.0},
		{"type": "rock", "lane": 1, "dist": 550.0},
		{"type": "rock", "lane": 0, "dist": 580.0},
		{"type": "rock", "lane": -1, "dist": 610.0},
		{"type": "rock", "lane": 1, "dist": 640.0},
		{"type": "rock", "lane": 0, "dist": 670.0},
		{"type": "rock", "lane": -1, "dist": 700.0},
		{"type": "rock", "lane": 1, "dist": 730.0},
		{"type": "rock", "lane": 0, "dist": 760.0},
		{"type": "rock", "lane": -1, "dist": 790.0},
		{"type": "rock", "lane": 1, "dist": 820.0},
		{"type": "rock", "lane": -1, "dist": 850.0},
		{"type": "rock", "lane": 1, "dist": 850.0},
		{"type": "rock", "lane": 0, "dist": 890.0},
		{"type": "rock", "lane": -1, "dist": 920.0},
		{"type": "rock", "lane": 1, "dist": 950.0},
		{"type": "rock", "lane": 0, "dist": 980.0},
		{"type": "rock", "lane": -1, "dist": 1010.0},
		{"type": "rock", "lane": 1, "dist": 1040.0},
		{"type": "rock", "lane": -1, "dist": 1070.0},
		{"type": "rock", "lane": 1, "dist": 1070.0},

		{"type": "hook", "lane": 0, "dist": 1130.0},
		{"type": "rapids", "lane": -1, "dist": 1180.0},
		{"type": "rapids", "lane": 1, "dist": 1180.0},
		{"type": "monkey", "lane": 0, "dist": 1230.0},
		{"type": "salmon", "lane": -1, "dist": 1280.0},
		{"type": "hook", "lane": 1, "dist": 1330.0},
		{"type": "ufo", "lane": 0, "dist": 1380.0},
		{"type": "rock", "lane": -1, "dist": 1430.0},
		{"type": "rock", "lane": 1, "dist": 1430.0},
		{"type": "updraft", "lane": 0, "dist": 1480.0},
		{"type": "monkey", "lane": -1, "dist": 1530.0},
		{"type": "salmon", "lane": 1, "dist": 1580.0},
		{"type": "hook", "lane": 0, "dist": 1630.0},
		{"type": "hook", "lane": -1, "dist": 1630.0},
		{"type": "breakable", "lane": 1, "dist": 1680.0},
		{"type": "ufo", "lane": -1, "dist": 1730.0},
		{"type": "rock", "lane": 0, "dist": 1780.0},
		{"type": "salmon", "lane": 1, "dist": 1830.0},
		{"type": "rock", "lane": 0, "dist": 1890.0},
		{"type": "rapids", "lane": -1, "dist": 1940.0},
		{"type": "rapids", "lane": 0, "dist": 1940.0},
		{"type": "monkey", "lane": 1, "dist": 1990.0},
		{"type": "hook", "lane": -1, "dist": 2040.0},
		{"type": "hook", "lane": 1, "dist": 2040.0},
		{"type": "breakable", "lane": 0, "dist": 2090.0},
		{"type": "salmon", "lane": -1, "dist": 2140.0},
		{"type": "salmon", "lane": 1, "dist": 2140.0},
		{"type": "updraft", "lane": 0, "dist": 2190.0},

		{"type": "breakable", "lane": -1, "dist": 2260.0},
		{"type": "rock", "lane": 0, "dist": 2290.0},
		{"type": "breakable", "lane": 1, "dist": 2320.0},
		{"type": "rock", "lane": -1, "dist": 2380.0},
		{"type": "rock", "lane": 1, "dist": 2380.0},
		{"type": "monkey", "lane": 0, "dist": 2430.0},
		{"type": "salmon", "lane": -1, "dist": 2480.0},
		{"type": "hook", "lane": 1, "dist": 2530.0},
		{"type": "hook", "lane": 0, "dist": 2530.0},
		{"type": "breakable", "lane": -1, "dist": 2580.0},
		{"type": "ufo", "lane": 1, "dist": 2630.0},
		{"type": "rock", "lane": 0, "dist": 2680.0},
		{"type": "rapids", "lane": -1, "dist": 2730.0},
		{"type": "monkey", "lane": 1, "dist": 2780.0},
		{"type": "salmon", "lane": 0, "dist": 2830.0},
		{"type": "hook", "lane": -1, "dist": 2880.0},
		{"type": "hook", "lane": 1, "dist": 2880.0},
		{"type": "breakable", "lane": 0, "dist": 2930.0},
		{"type": "ufo", "lane": -1, "dist": 2980.0},
		{"type": "rock", "lane": 1, "dist": 3030.0},
		{"type": "salmon", "lane": 0, "dist": 3090.0},
		{"type": "monkey", "lane": -1, "dist": 3140.0},
		{"type": "salmon", "lane": 1, "dist": 3190.0},
		{"type": "hook", "lane": 0, "dist": 3240.0},
		{"type": "rock", "lane": -1, "dist": 3290.0},
		{"type": "rock", "lane": 1, "dist": 3290.0},
		{"type": "updraft", "lane": -1, "dist": 3350.0},
		{"type": "updraft", "lane": 0, "dist": 3350.0},
		{"type": "updraft", "lane": 1, "dist": 3350.0}
	]
}
